robocivix/__init__.py
robocivix-0.0.1.dist-info/METADATA
robocivix-0.0.1.dist-info/WHEEL
robocivix-0.0.1.dist-info/entry_points.txt
robocivix-0.0.1.dist-info/top_level.txt
robocivix-0.0.1.dist-info/RECORD
