Metadata-Version: 2.1
Name: robocivix
Version: 0.0.1
Summary: RoboCivix
Author-email: Nanw1103 <nanw1103@gmail.com>
Project-URL: Homepage, https://github.com/nanw1103/robocivix
Project-URL: Bug Tracker, https://github.com/nanw1103/robocivix/issues
Project-URL: documentation, https://readthedocs.org
Project-URL: repository, https://github.com/nanw1103/robocivix
Project-URL: changelog, https://github.com/nanw1103/robocivix/blob/main/CHANGELOG.md
Keywords: RoboCivix,Simulation
Classifier: Programming Language :: Python :: 3
Classifier: Development Status :: 4 - Beta
Classifier: License :: OSI Approved :: MIT License
Classifier: Operating System :: OS Independent
Requires-Python: >=3.10
Requires-Dist: httpx
